README
setup.py
Adjax.egg-info/PKG-INFO
Adjax.egg-info/SOURCES.txt
Adjax.egg-info/dependency_links.txt
Adjax.egg-info/requires.txt
Adjax.egg-info/top_level.txt
adjax/__init__.py
adjax/base.py
adjax/decorators.py
adjax/models.py
adjax/utils.py
adjax/templatetags/__init__.py
adjax/templatetags/ajax.py