Metadata-Version: 1.0
Name: Adjax
Version: 1.0.1
Summary: A framework for easing the development of Django sites with Ajax.
Home-page: http://adjax.hardysoftware.com.au/
Author: Will Hardy
Author-email: adjax@hardysoftware.com.au
License: New BSD
Keywords: ajax,django,framework
Platform: UNKNOWN
